pyhtrie/__init__.py
pyhtrie/htrie.py
pyhtrie/trie_node.py
pyhtrie-1.0.0.dist-info/LICENSE
pyhtrie-1.0.0.dist-info/METADATA
pyhtrie-1.0.0.dist-info/WHEEL
pyhtrie-1.0.0.dist-info/top_level.txt
pyhtrie-1.0.0.dist-info/RECORD
