Metadata-Version: 2.1
Name: pyhtrie
Version: 1.0.0
Summary: Hashed Trie data structure for faster memory efficient and fast keyword indexing and lookup
Home-page: https://github.com/aronsajan/pyhtrie/tree/master
Author: Aron Sajan Philip
Author-email: arondeveloper@yahoo.com
License: MIT
Platform: UNKNOWN
